discordapiwebhooks/discordapiwebhooks.py
discordapiwebhooks/setup.py
discordapiwebhooks-1.0.2.dist-info/METADATA
discordapiwebhooks-1.0.2.dist-info/WHEEL
discordapiwebhooks-1.0.2.dist-info/top_level.txt
discordapiwebhooks-1.0.2.dist-info/RECORD
