Metadata-Version: 2.1
Name: discordapiwebhooks
Version: 1.0.2
Summary: discordapiwebhooks is a Python module that allows you to easily send webhooks to Discord. It supports sending text, images, and files to a Discord server.
Home-page: UNKNOWN
Author: NouName
Author-email: duaneskalanak@gmail.com
License: UNKNOWN
Platform: UNKNOWN
